{
    "last_update": "29.09.2025 15:28",
    "moves_up": {
        "record": 0,
        "last_update": "25.09.2025 17:07",
        "updated_by": "ae0ac937"
    },
    "moves_down": {
        "record": 0,
        "last_update": "25.09.2025 15:31",
        "updated_by": "f0e300bc"
    },
    "moves_left": {
        "record": 0,
        "last_update": "25.09.2025 17:07",
        "updated_by": "ae0ac937"
    },
    "moves_right": {
        "record": 0,
        "last_update": "25.09.2025 17:07",
        "updated_by": "07480532"
    },
    "total_moves": {
        "record": 12,
        "last_update": "25.09.2025 17:08",
        "updated_by": "3f02eea7"
    },
    "max_value_on_gameboard": {
        "record": 2048,
        "last_update": "29.09.2025 15:28",
        "updated_by": "3b7a6bd9"
    }
}